goosebit_simple_stats/__init__.py
goosebit_simple_stats/api/__init__.py
goosebit_simple_stats/api/routes.py
goosebit_simple_stats/api/v1/__init__.py
goosebit_simple_stats/api/v1/routes.py
goosebit_simple_stats/api/v1/stats/__init__.py
goosebit_simple_stats/api/v1/stats/responses.py
goosebit_simple_stats/api/v1/stats/routes.py
goosebit_simple_stats/schema/__init__.py
goosebit_simple_stats/schema/show.py
goosebit_simple_stats/settings/__init__.py
goosebit_simple_stats/settings/const.py
goosebit_simple_stats/settings/schema.py
goosebit_simple_stats/ui/__init__.py
goosebit_simple_stats/ui/bff/__init__.py
goosebit_simple_stats/ui/bff/stats/__init__.py
goosebit_simple_stats/ui/bff/stats/routes.py
goosebit_simple_stats/ui/routes.py
goosebit_simple_stats/ui/static/__init__.py
goosebit_simple_stats/ui/static/js/stats.js
goosebit_simple_stats/ui/templates/__init__.py
goosebit_simple_stats/ui/templates/stats.html.jinja
goosebit_simple_stats-0.1.1.dist-info/METADATA
goosebit_simple_stats-0.1.1.dist-info/WHEEL
goosebit_simple_stats-0.1.1.dist-info/entry_points.txt
goosebit_simple_stats-0.1.1.dist-info/RECORD
