Metadata-Version: 2.3
Name: goosebit-simple-stats
Version: 0.1.1
Summary: gooseBit plugin showing some basic statistics
Author: Brett Rowan
Author-email: 121075405+b-rowan@users.noreply.github.com
Requires-Python: >=3.11,<4.0
Classifier: Programming Language :: Python :: 3
Classifier: Programming Language :: Python :: 3.11
Classifier: Programming Language :: Python :: 3.12
Classifier: Programming Language :: Python :: 3.13
Requires-Dist: goosebit
